minimcp/__init__.py
minimcp/server/__init__.py
minimcp/server/exceptions.py
minimcp/server/json_rpc.py
minimcp/server/limiter.py
minimcp/server/minimcp.py
minimcp/server/responder.py
minimcp/server/types.py
minimcp/server/managers/context_manager.py
minimcp/server/managers/prompt_manager.py
minimcp/server/managers/resource_manager.py
minimcp/server/managers/tool_manager.py
minimcp/server/transports/http.py
minimcp/server/transports/http_transport_base.py
minimcp/server/transports/starlette.py
minimcp/server/transports/stdio.py
minimcp/server/transports/streamable_http.py
minimcp/utils/func.py
minimcp/utils/model.py
minimcp/utils/task_status_wrapper.py
minimcp-0.3.7.dist-info/METADATA
minimcp-0.3.7.dist-info/WHEEL
minimcp-0.3.7.dist-info/licenses/LICENSE
minimcp-0.3.7.dist-info/RECORD
