Metadata-Version: 2.4
Name: minimcp
Version: 0.3.7
Summary: A minimal, stateless, and lightweight framework for building remote MCP servers.
Author-email: Sreenath Somarajapuram <somarajapuram@gmail.com>
License:                                  Apache License
License-File: LICENSE
Requires-Python: >=3.10
Requires-Dist: mcp>=1.12.3
